reva_coregistration/__init__.py
reva_coregistration/coordinates.py
reva_coregistration/coregistration.py
reva_coregistration/globals.py
reva_coregistration/image_utils.py
reva_coregistration/landmarks.py
reva_coregistration/logger.py
reva_coregistration/paths.py
reva_coregistration/plotly_viewer.py
reva_coregistration/slices.py
reva_coregistration/tiles.py
reva_coregistration/transformations.py
reva_coregistration/warping.py
reva_coregistration-1.0.1.dist-info/licenses/LICENSE
reva_coregistration-1.0.1.dist-info/METADATA
reva_coregistration-1.0.1.dist-info/WHEEL
reva_coregistration-1.0.1.dist-info/top_level.txt
reva_coregistration-1.0.1.dist-info/RECORD
