Metadata-Version: 2.4
Name: reva-coregistration
Version: 1.0.1
Summary: A Python package for image coregistration and coordinate transformation
Author-email: "Robert Toth, PhD" <robert.toth@thetatech.ai>
Maintainer-email: "Robert Toth, PhD" <robert.toth@thetatech.ai>
License-Expression: MIT
Project-URL: Homepage, https://github.com/Theta-Tech-AI/reva-coregistration
Project-URL: Repository, https://github.com/Theta-Tech-AI/reva-coregistration
Project-URL: Documentation, https://github.com/Theta-Tech-AI/reva-coregistration#readme
Project-URL: Bug Tracker, https://github.com/Theta-Tech-AI/reva-coregistration/issues
Keywords: coregistration,image-processing,coordinate-transformation,medical-imaging
Classifier: Development Status :: 3 - Alpha
Classifier: Intended Audience :: Science/Research
Classifier: Programming Language :: Python :: 3
Classifier: Programming Language :: Python :: 3.8
Classifier: Programming Language :: Python :: 3.9
Classifier: Programming Language :: Python :: 3.10
Classifier: Programming Language :: Python :: 3.11
Classifier: Topic :: Scientific/Engineering :: Image Processing
Classifier: Topic :: Scientific/Engineering :: Medical Science Apps.
Requires-Python: >=3.8
License-File: LICENSE
Requires-Dist: numpy>=1.21.0
Requires-Dist: opencv-python>=4.5.0
Requires-Dist: opencv-contrib-python-headless>=4.5.0
Requires-Dist: Pillow>=8.0.0
Requires-Dist: pyvips>=2.1.0
Requires-Dist: scipy>=1.7.0
Requires-Dist: scikit-learn>=1.0.0
Provides-Extra: dev
Requires-Dist: pytest>=6.0.0; extra == "dev"
Requires-Dist: pytest-cov>=2.0.0; extra == "dev"
Requires-Dist: black>=21.0.0; extra == "dev"
Requires-Dist: flake8>=3.8.0; extra == "dev"
Requires-Dist: mypy>=0.800; extra == "dev"
Dynamic: license-file
